website_crawler_sdk/__init__.py
website_crawler_sdk/client.py
website_crawler_sdk/config.py
website_crawler_sdk-0.1.5.dist-info/licenses/LICENSE.txt
website_crawler_sdk-0.1.5.dist-info/METADATA
website_crawler_sdk-0.1.5.dist-info/WHEEL
website_crawler_sdk-0.1.5.dist-info/top_level.txt
website_crawler_sdk-0.1.5.dist-info/RECORD
