Metadata-Version: 2.4
Name: website_crawler_sdk
Version: 0.1.5
Summary: The official Python SDK for the Website Crawler API
Home-page: https://www.websitecrawler.org
Author: Pramod Choudhary
Requires-Python: >=3.6
License-File: LICENSE.txt
Requires-Dist: requests
Dynamic: author
Dynamic: description
Dynamic: description-content-type
Dynamic: home-page
Dynamic: license-file
Dynamic: requires-dist
Dynamic: requires-python
Dynamic: summary
